poetry_pep440_plugin/plugin.py
poetry_pep440_plugin-0.1.3.dist-info/entry_points.txt
poetry_pep440_plugin-0.1.3.dist-info/WHEEL
poetry_pep440_plugin-0.1.3.dist-info/METADATA
poetry_pep440_plugin-0.1.3.dist-info/RECORD
